accounts/__init__.py
accounts/adapter.py
accounts/admin.py
accounts/forms.py
accounts/locale/vi/LC_MESSAGES/django.mo
accounts/locale/vi/LC_MESSAGES/django.po
accounts/settings.py
accounts/signals.py
accounts/templates/accounts/base_site.html
accounts/templates/accounts/home.html
accounts/templates/accounts/includes/fieldset.html
accounts/templates/accounts/logged_out.html
accounts/templates/accounts/login_form.html
accounts/templates/accounts/password_change_done.html
accounts/templates/accounts/password_change_form.html
accounts/templates/accounts/password_reset_complete.html
accounts/templates/accounts/password_reset_confirm.html
accounts/templates/accounts/password_reset_done.html
accounts/templates/accounts/password_reset_email.html
accounts/templates/accounts/password_reset_form.html
accounts/templates/accounts/profile_form.html
accounts/templatetags/__init__.py
accounts/templatetags/form_tags.py
accounts/urls.py
accounts/views.py
django_simple_accounts-0.1.3.dist-info/METADATA
django_simple_accounts-0.1.3.dist-info/WHEEL
django_simple_accounts-0.1.3.dist-info/RECORD
