Metadata-Version: 2.1
Name: django-simple-accounts
Version: 0.1.3
Summary: Django accounts site
Home-page: https://github.com/ThuanD/django-simple-accounts
Author: kai
Author-email: thuan.dv0@gmail.com
Requires-Python: >=3.10,<4.0
Classifier: Programming Language :: Python :: 3
Classifier: Programming Language :: Python :: 3.10
Classifier: Programming Language :: Python :: 3.11
Classifier: Programming Language :: Python :: 3.12
Requires-Dist: django (>=5.1.1,<6.0.0)
Project-URL: Repository, https://github.com/ThuanD/django-simple-accounts
